[{"title":"2026 AI활용 마케팅 경진대회 (영상 작품 제작 관련 및 제출) 안내","link":"https://cn.korchamhrd.net/bbs/bbsDetail.do?rootMenuId=3766&menuId=3767&bbs_id=141&bbs_key=226980","date":"2026-05-14"},{"title":"[공모전] 2026년 AI 콘텐츠 마케팅 챌린지 공모전 안내(재공고)","link":"https://cn.korchamhrd.net/bbs/bbsDetail.do?rootMenuId=3766&menuId=3767&bbs_id=141&bbs_key=226714","date":"2026-04-14"},{"title":"취·창업 CDP 지원 프로그램 [충청권 ICT 기업탐방·채용연계 참여기업 모집]","link":"https://cn.korchamhrd.net/bbs/bbsDetail.do?rootMenuId=3766&menuId=3767&bbs_id=141&bbs_key=228158","date":"2026-06-23"},{"title":"기간제 근로자(행정사무원_이노베이션전담자) “긴급” 채용 공고","link":"https://cn.korchamhrd.net/bbs/bbsDetail.do?rootMenuId=3766&menuId=3767&bbs_id=141&bbs_key=228060","date":"2026-06-19"},{"title":"(ICT사업) ICT 이노베이션스퀘어 확산사업 기업협력프로젝트","link":"https://cn.korchamhrd.net/bbs/bbsDetail.do?rootMenuId=3766&menuId=3767&bbs_id=141&bbs_key=227976","date":"2026-06-12"}]